<annotation>
    <folder>soccer</folder>
    <filename>Screen Shot 2018-05-03 at 5.32.20 PM.png</filename>
    <size>
        <width>2560</width>
        <height>1600</height>
        <depth>3</depth>
    </size>
    <segmented>0</segmented>
    <object>
        <name>soccer ball</name>
        <pose>Unspecified</pose>
        <truncated>0</truncated>
        <occluded>0</occluded>
        <difficult>0</difficult>
        <bndbox>
            <xmin>748</xmin>
            <ymin>901</ymin>
            <xmax>834</xmax>
            <ymax>972</ymax>
        </bndbox>
    </object>
    <object>
        <name>referee</name>
        <pose>Unspecified</pose>
        <truncated>0</truncated>
        <occluded>0</occluded>
        <difficult>0</difficult>
        <bndbox>
            <xmin>1489</xmin>
            <ymin>1331</ymin>
            <xmax>1723</xmax>
            <ymax>1478</ymax>
        </bndbox>
    </object>
    <object>
        <name>referee</name>
        <pose>Unspecified</pose>
        <truncated>0</truncated>
        <occluded>0</occluded>
        <difficult>0</difficult>
        <bndbox>
            <xmin>1938</xmin>
            <ymin>248</ymin>
            <xmax>2095</xmax>
            <ymax>653</ymax>
        </bndbox>
    </object>
    <object>
        <name>soccer player</name>
        <pose>Unspecified</pose>
        <truncated>0</truncated>
        <occluded>0</occluded>
        <difficult>0</difficult>
        <bndbox>
            <xmin>203</xmin>
            <ymin>268</ymin>
            <xmax>346</xmax>
            <ymax>561</ymax>
        </bndbox>
    </object>
    <object>
        <name>soccer player</name>
        <pose>Unspecified</pose>
        <truncated>0</truncated>
        <occluded>0</occluded>
        <difficult>0</difficult>
        <bndbox>
            <xmin>1</xmin>
            <ymin>332</ymin>
            <xmax>137</xmax>
            <ymax>720</ymax>
        </bndbox>
    </object>
    <object>
        <name>soccer player</name>
        <pose>Unspecified</pose>
        <truncated>0</truncated>
        <occluded>0</occluded>
        <difficult>0</difficult>
        <bndbox>
            <xmin>401</xmin>
            <ymin>428</ymin>
            <xmax>650</xmax>
            <ymax>732</ymax>
        </bndbox>
    </object>
    <object>
        <name>soccer player</name>
        <pose>Unspecified</pose>
        <truncated>0</truncated>
        <occluded>0</occluded>
        <difficult>0</difficult>
        <bndbox>
            <xmin>552</xmin>
            <ymin>503</ymin>
            <xmax>869</xmax>
            <ymax>909</ymax>
        </bndbox>
    </object>
</annotation>