<annotation>
    <folder>basketball_training_imgs</folder>
    <filename>58.png</filename>
    <size>
        <width>2760</width>
        <height>1418</height>
        <depth>3</depth>
    </size>
    <segmented>0</segmented>
    <object>
        <name>player</name>
        <pose>Unspecified</pose>
        <truncated>0</truncated>
        <occluded>0</occluded>
        <difficult>0</difficult>
        <bndbox>
            <xmin>544</xmin>
            <ymin>835</ymin>
            <xmax>749</xmax>
            <ymax>1414</ymax>
        </bndbox>
    </object>
    <object>
        <name>player</name>
        <pose>Unspecified</pose>
        <truncated>0</truncated>
        <occluded>0</occluded>
        <difficult>0</difficult>
        <bndbox>
            <xmin>676</xmin>
            <ymin>551</ymin>
            <xmax>838</xmax>
            <ymax>989</ymax>
        </bndbox>
    </object>
    <object>
        <name>player</name>
        <pose>Unspecified</pose>
        <truncated>0</truncated>
        <occluded>0</occluded>
        <difficult>0</difficult>
        <bndbox>
            <xmin>1208</xmin>
            <ymin>1137</ymin>
            <xmax>1475</xmax>
            <ymax>1418</ymax>
        </bndbox>
    </object>
    <object>
        <name>player</name>
        <pose>Unspecified</pose>
        <truncated>0</truncated>
        <occluded>0</occluded>
        <difficult>0</difficult>
        <bndbox>
            <xmin>1486</xmin>
            <ymin>684</ymin>
            <xmax>1766</xmax>
            <ymax>1391</ymax>
        </bndbox>
    </object>
    <object>
        <name>player</name>
        <pose>Unspecified</pose>
        <truncated>0</truncated>
        <occluded>0</occluded>
        <difficult>0</difficult>
        <bndbox>
            <xmin>871</xmin>
            <ymin>861</ymin>
            <xmax>1423</xmax>
            <ymax>1112</ymax>
        </bndbox>
    </object>
</annotation>